dbconvert/__init__.py
dbconvert/cli.py
dbconvert/converters/__init__.py
dbconvert/converters/base_converter.py
dbconvert/converters/converter_factory.py
dbconvert/converters/mysql_converter.py
dbconvert/converters/postgres_converter.py
dbconvert/core/__init__.py
dbconvert/core/enums.py
dbconvert/core/loggingsetup.py
dbconvert/core/metadata.py
dbconvert/gui/__init__.py
dbconvert/gui/app.py
dbconvert/gui/assets/logo.png
dbconvert/writers/__init__.py
dbconvert/writers/sqlite_writer.py
dbconvert-1.2.0.dist-info/licenses/LICENSE
dbconvert-1.2.0.dist-info/METADATA
dbconvert-1.2.0.dist-info/WHEEL
dbconvert-1.2.0.dist-info/entry_points.txt
dbconvert-1.2.0.dist-info/top_level.txt
dbconvert-1.2.0.dist-info/RECORD
