Metadata-Version: 2.4
Name: dbconvert
Version: 1.2.0
Summary: A CLI and GUI tool to convert PostgreSQL/MySQL databases to SQLite
Author-email: ysskrishna <sivasaikrishnassk@gmail.com>
License: MIT
Project-URL: Homepage, https://github.com/ysskrishna/dbconvert
Project-URL: Documentation, https://github.com/ysskrishna/dbconvert#readme
Project-URL: Repository, https://github.com/ysskrishna/dbconvert.git
Project-URL: Issues, https://github.com/ysskrishna/dbconvert/issues
Keywords: database,sqlite,postgresql,mysql,conversion,cli,gui,tkinter,desktop
Classifier: Programming Language :: Python :: 3
Classifier: License :: OSI Approved :: MIT License
Classifier: Operating System :: OS Independent
Classifier: Typing :: Typed
Classifier: Development Status :: 5 - Production/Stable
Classifier: Intended Audience :: Developers
Classifier: Topic :: Database
Classifier: Topic :: Software Development :: Libraries :: Python Modules
Requires-Python: >=3.8
License-File: LICENSE
Requires-Dist: typer==0.15.4
Requires-Dist: rich==14.0.0
Requires-Dist: SQLAlchemy==2.0.41
Requires-Dist: psycopg2-binary==2.9.10
Requires-Dist: PyMySQL==1.1.1
Requires-Dist: tomli; python_version < "3.11"
Provides-Extra: gui
Requires-Dist: Pillow>=10.0.0; extra == "gui"
Dynamic: license-file
